MANIFEST.in
README.markdown
setup.py
src/IterDict.egg-info/PKG-INFO
src/IterDict.egg-info/SOURCES.txt
src/IterDict.egg-info/dependency_links.txt
src/IterDict.egg-info/top_level.txt
src/iterdict/__init__.py
src/iterdict/test/__init__.py
src/iterdict/test/bench.py
src/iterdict/test/test_iterdict.py