Metadata-Version: 1.0
Name: IterDict
Version: 0.2.0
Summary: Dict that lazily populates itself with items from the iterator it was constructed with as keys are accessed
Home-page: http://packages.python.org/an_example_pypi_project
Author: Kirk Strauser
Author-email: kirk@strauser.com
License: BSD
Keywords: dict lazy bigdata
Platform: UNKNOWN
Classifier: Development Status :: 4 - Beta
Classifier: Intended Audience :: Developers
Classifier: Programming Language :: Python :: 2
Classifier: Programming Language :: Python :: 2.5
Classifier: Programming Language :: Python :: 2.6
Classifier: Programming Language :: Python :: 2.7
Classifier: Programming Language :: Python :: 3
Classifier: Programming Language :: Python :: 3.2
Classifier: Topic :: Software Development :: Libraries
Classifier: License :: OSI Approved :: BSD License
